pypdu.pypy310-pp73-darwin.so
pypdu-0.1.10.dist-info/RECORD
pypdu-0.1.10.dist-info/LICENSE
pypdu-0.1.10.dist-info/WHEEL
pypdu-0.1.10.dist-info/NOTICE
pypdu-0.1.10.dist-info/top_level.txt
pypdu-0.1.10.dist-info/METADATA
